[{"_distance":1.16803877654789,"Provider":{"ProviderNumber":"C01OK0062 ","Name":"Shalimar United Methodist Preschool","Capacity":115,"LicenseExpirationDate":"12/31/2017","IsReligiousExempt":false,"IsFaithBased":true,"IsHeadStart":false,"IsOfferingSchoolReadiness":false,"IsPublicSchool":false,"OriginationDate":"03/01/1986","ProviderID":35448,"AddressID":11842,"StreetNumber":"1","StreetPreDirection":null,"StreetName":"Old Ferry","StreetSuffix":"Rd","StreetPostDirection":null,"SecondaryDesignatorPrefix":null,"SecondaryDesignatorSuffix":null,"ExtraSecondaryDesignatorPrefix":null,"ExtraSecondaryDesignatorSuffix":null,"City":"Shalimar","County":"Okaloosa","State":"FL","ZipCode":"32579","ZipPlus4":"1212","Latitude":30.437950,"Longitude":-86.582310,"DisplayAddressOnWeb":true,"PhoneNumber":8506510721,"DisplayPhoneOnWeb":true,"ProgramType":"Child Care Facility","Status":"Regular/Annual","Services":"Half Day;School Year Only","FullAddress":"1 Old Ferry Rd, Shalimar FL 32579-1212","GoldSealAccreditingAgency":null,"GoldSealEffectiveDate":null,"GoldSealExpirationDate":null,"GoldSealStatusID":null,"MondayHours":" 8:45AM to 2:00PM","TuesdayHours":" 8:45AM to 2:00PM","WednesdayHours":" 8:45AM to 2:00PM","ThursdayHours":" 8:45AM to 2:00PM","FridayHours":" 8:45AM to 12:15PM","SaturdayHours":null,"SundayHours":null,"LicenseStatus":"Licensed","DBAName":null,"IsVPK":true,"VpkStatusID":2,"AgencyID":2,"AlternateProviderNumber":null,"Inspections":[{"InspectionID":279847,"HasViolation":false,"InspectionDate":"2014-07-21 13:59:00","ProviderID":35448,"AgencyID":0},{"InspectionID":290864,"HasViolation":false,"InspectionDate":"2015-07-21 09:30:00","ProviderID":35448,"AgencyID":0},{"InspectionID":305129,"HasViolation":false,"InspectionDate":"2015-03-17 10:55:00","ProviderID":35448,"AgencyID":0},{"InspectionID":310150,"HasViolation":false,"InspectionDate":"2014-12-03 09:30:00","ProviderID":35448,"AgencyID":0},{"InspectionID":346831,"HasViolation":false,"InspectionDate":"2015-12-09 13:05:00","ProviderID":35448,"AgencyID":0},{"InspectionID":360541,"HasViolation":true,"InspectionDate":"2016-04-06 10:15:00","ProviderID":35448,"AgencyID":0},{"InspectionID":361645,"HasViolation":false,"InspectionDate":"2016-04-22 11:36:00","ProviderID":35448,"AgencyID":0},{"InspectionID":371782,"HasViolation":false,"InspectionDate":"2016-08-10 16:35:00","ProviderID":35448,"AgencyID":0},{"InspectionID":383622,"HasViolation":false,"InspectionDate":"2016-12-07 12:57:00","ProviderID":35448,"AgencyID":0},{"InspectionID":398922,"HasViolation":false,"InspectionDate":"2017-04-26 12:58:00","ProviderID":35448,"AgencyID":0}],"VPKAccreditation":[],"VPKClass":[{"ID":"2d4a851f-4026-47de-8626-56e98bfcea60","ProviderID":35448,"ClassRoomCode":"A16","ClassType":"540","StartDate":"09/06/2016","EndDate":"05/18/2017","Monday":"8:45AM to 12:15PM","Tuesday":"8:45AM to 12:15PM","Wednesday":"8:45AM to 12:15PM","Thursday":"8:45AM to 12:15PM","Friday":"8:45AM to 12:15PM","Saturday":null,"Sunday":null,"ClassRoomCount":1,"Capacity":11,"Enrollments":11,"InstructorCredential":"Bachelor\u0027s Degree","AgencyID":2},{"ID":"f4cadd40-e686-4f21-8ed9-fc15dd63c8bf","ProviderID":35448,"ClassRoomCode":"B16","ClassType":"540","StartDate":"09/06/2016","EndDate":"05/18/2017","Monday":"8:45AM to 12:15PM","Tuesday":"8:45AM to 12:15PM","Wednesday":"8:45AM to 12:15PM","Thursday":"8:45AM to 12:15PM","Friday":"8:45AM to 12:15PM","Saturday":null,"Sunday":null,"ClassRoomCount":1,"Capacity":11,"Enrollments":11,"InstructorCredential":"Florida Equivalent Credential: FCCPC/ECPC/CCAC/CDAE","AgencyID":2},{"ID":"7ea0a6ef-2c55-4de4-b083-9a7767c65659","ProviderID":35448,"ClassRoomCode":"C16","ClassType":"540","StartDate":"09/06/2016","EndDate":"05/18/2017","Monday":"8:45AM to 12:15PM","Tuesday":"8:45AM to 12:15PM","Wednesday":"8:45AM to 12:15PM","Thursday":"8:45AM to 12:15PM","Friday":"8:45AM to 12:15PM","Saturday":null,"Sunday":null,"ClassRoomCount":1,"Capacity":11,"Enrollments":11,"InstructorCredential":"Associate Degree","AgencyID":2},{"ID":"e44fe974-4cb3-4dd2-bbbf-a9e86c9c88df","ProviderID":35448,"ClassRoomCode":"D16","ClassType":"540","StartDate":"09/06/2016","EndDate":"05/18/2017","Monday":"8:45AM to 12:15PM","Tuesday":"8:45AM to 12:15PM","Wednesday":"8:45AM to 12:15PM","Thursday":"8:45AM to 12:15PM","Friday":"8:45AM to 12:15PM","Saturday":null,"Sunday":null,"ClassRoomCount":1,"Capacity":11,"Enrollments":11,"InstructorCredential":"Associate Degree","AgencyID":2},{"ID":"07f10d9a-d101-4523-87f8-66ad50a664e1","ProviderID":35448,"ClassRoomCode":"E16","ClassType":"540","StartDate":"09/06/2016","EndDate":"05/18/2017","Monday":"8:45AM to 12:15PM","Tuesday":"8:45AM to 12:15PM","Wednesday":"8:45AM to 12:15PM","Thursday":"8:45AM to 12:15PM","Friday":"8:45AM to 12:15PM","Saturday":null,"Sunday":null,"ClassRoomCount":1,"Capacity":11,"Enrollments":10,"InstructorCredential":"National Early Childhood Certificate","AgencyID":2}],"VPKCurriculum":[{"ID":"b1207899-e485-48d9-9f75-1a5d4263520f","ProviderID":35448,"Description":"CREATE PRESCHOOL","PublisherName":null},{"ID":"3fbaf001-3053-4c65-a5ca-790ad2d9b634","ProviderID":35448,"Description":"WEE LEARN","PublisherName":null}]},"reportIDs":null,"_displayDistance":true,"Inspections":[{"InspectionID":398922,"HasViolation":false,"InspectionDate":"2017-04-26 12:58:00","ProviderID":35448,"AgencyID":0},{"InspectionID":383622,"HasViolation":false,"InspectionDate":"2016-12-07 12:57:00","ProviderID":35448,"AgencyID":0},{"InspectionID":371782,"HasViolation":false,"InspectionDate":"2016-08-10 16:35:00","ProviderID":35448,"AgencyID":0},{"InspectionID":361645,"HasViolation":false,"InspectionDate":"2016-04-22 11:36:00","ProviderID":35448,"AgencyID":0},{"InspectionID":360541,"HasViolation":true,"InspectionDate":"2016-04-06 10:15:00","ProviderID":35448,"AgencyID":0},{"InspectionID":346831,"HasViolation":false,"InspectionDate":"2015-12-09 13:05:00","ProviderID":35448,"AgencyID":0},{"InspectionID":290864,"HasViolation":false,"InspectionDate":"2015-07-21 09:30:00","ProviderID":35448,"AgencyID":0},{"InspectionID":305129,"HasViolation":false,"InspectionDate":"2015-03-17 10:55:00","ProviderID":35448,"AgencyID":0},{"InspectionID":310150,"HasViolation":false,"InspectionDate":"2014-12-03 09:30:00","ProviderID":35448,"AgencyID":0},{"InspectionID":279847,"HasViolation":false,"InspectionDate":"2014-07-21 13:59:00","ProviderID":35448,"AgencyID":0}],"VPKAccreditation":[],"VPKClass":[{"ID":"2d4a851f-4026-47de-8626-56e98bfcea60","ProviderID":35448,"ClassRoomCode":"A16","ClassType":"540","StartDate":"09/06/2016","EndDate":"05/18/2017","Monday":"8:45AM to 12:15PM","Tuesday":"8:45AM to 12:15PM","Wednesday":"8:45AM to 12:15PM","Thursday":"8:45AM to 12:15PM","Friday":"8:45AM to 12:15PM","Saturday":null,"Sunday":null,"ClassRoomCount":1,"Capacity":11,"Enrollments":11,"InstructorCredential":"Bachelor\u0027s Degree","AgencyID":2},{"ID":"f4cadd40-e686-4f21-8ed9-fc15dd63c8bf","ProviderID":35448,"ClassRoomCode":"B16","ClassType":"540","StartDate":"09/06/2016","EndDate":"05/18/2017","Monday":"8:45AM to 12:15PM","Tuesday":"8:45AM to 12:15PM","Wednesday":"8:45AM to 12:15PM","Thursday":"8:45AM to 12:15PM","Friday":"8:45AM to 12:15PM","Saturday":null,"Sunday":null,"ClassRoomCount":1,"Capacity":11,"Enrollments":11,"InstructorCredential":"Florida Equivalent Credential: FCCPC/ECPC/CCAC/CDAE","AgencyID":2},{"ID":"7ea0a6ef-2c55-4de4-b083-9a7767c65659","ProviderID":35448,"ClassRoomCode":"C16","ClassType":"540","StartDate":"09/06/2016","EndDate":"05/18/2017","Monday":"8:45AM to 12:15PM","Tuesday":"8:45AM to 12:15PM","Wednesday":"8:45AM to 12:15PM","Thursday":"8:45AM to 12:15PM","Friday":"8:45AM to 12:15PM","Saturday":null,"Sunday":null,"ClassRoomCount":1,"Capacity":11,"Enrollments":11,"InstructorCredential":"Associate Degree","AgencyID":2},{"ID":"e44fe974-4cb3-4dd2-bbbf-a9e86c9c88df","ProviderID":35448,"ClassRoomCode":"D16","ClassType":"540","StartDate":"09/06/2016","EndDate":"05/18/2017","Monday":"8:45AM to 12:15PM","Tuesday":"8:45AM to 12:15PM","Wednesday":"8:45AM to 12:15PM","Thursday":"8:45AM to 12:15PM","Friday":"8:45AM to 12:15PM","Saturday":null,"Sunday":null,"ClassRoomCount":1,"Capacity":11,"Enrollments":11,"InstructorCredential":"Associate Degree","AgencyID":2},{"ID":"07f10d9a-d101-4523-87f8-66ad50a664e1","ProviderID":35448,"ClassRoomCode":"E16","ClassType":"540","StartDate":"09/06/2016","EndDate":"05/18/2017","Monday":"8:45AM to 12:15PM","Tuesday":"8:45AM to 12:15PM","Wednesday":"8:45AM to 12:15PM","Thursday":"8:45AM to 12:15PM","Friday":"8:45AM to 12:15PM","Saturday":null,"Sunday":null,"ClassRoomCount":1,"Capacity":11,"Enrollments":10,"InstructorCredential":"National Early Childhood Certificate","AgencyID":2}],"VPKCurriculum":[{"ID":"b1207899-e485-48d9-9f75-1a5d4263520f","ProviderID":35448,"Description":"CREATE PRESCHOOL","PublisherName":null},{"ID":"3fbaf001-3053-4c65-a5ca-790ad2d9b634","ProviderID":35448,"Description":"WEE LEARN","PublisherName":null}],"Distance":"1.17 miles","DisplayServices":{"Half Day":1,"School Year Only":1}},{"_distance":1.34782401298845,"Provider":{"ProviderNumber":"C01OK0028 ","Name":"Dimples Day Care Center","Capacity":60,"LicenseExpirationDate":"05/31/2018","IsReligiousExempt":false,"IsFaithBased":false,"IsHeadStart":false,"IsOfferingSchoolReadiness":false,"IsPublicSchool":false,"OriginationDate":"06/01/1987","ProviderID":36006,"AddressID":19228,"StreetNumber":"34","StreetPreDirection":null,"StreetName":"8th","StreetSuffix":"St","StreetPostDirection":null,"SecondaryDesignatorPrefix":null,"SecondaryDesignatorSuffix":null,"ExtraSecondaryDesignatorPrefix":null,"ExtraSecondaryDesignatorSuffix":null,"City":"Shalimar","County":"Okaloosa","State":"FL","ZipCode":"32579","ZipPlus4":"1938","Latitude":30.440885,"Longitude":-86.569444,"DisplayAddressOnWeb":true,"PhoneNumber":8506512868,"DisplayPhoneOnWeb":true,"ProgramType":"Child Care Facility","Status":"Regular/Annual","Services":"After School;Before School;Drop In;Food Served;Full Day;Half Day;Open Year-Round","FullAddress":"34 8th St, Shalimar FL 32579-1938","GoldSealAccreditingAgency":null,"GoldSealEffectiveDate":null,"GoldSealExpirationDate":null,"GoldSealStatusID":null,"MondayHours":" 6:30AM to 6:00PM","TuesdayHours":" 6:30AM to 6:00PM","WednesdayHours":" 6:30AM to 6:00PM","ThursdayHours":" 6:30AM to 6:00PM","FridayHours":" 6:30AM to 6:00PM","SaturdayHours":null,"SundayHours":null,"LicenseStatus":"Licensed","DBAName":null,"IsVPK":false,"VpkStatusID":1,"AgencyID":2,"AlternateProviderNumber":null,"Inspections":[{"InspectionID":296905,"HasViolation":true,"InspectionDate":"2015-05-05 13:05:00","ProviderID":36006,"AgencyID":0},{"InspectionID":305269,"HasViolation":false,"InspectionDate":"2015-06-08 09:38:00","ProviderID":36006,"AgencyID":0},{"InspectionID":310773,"HasViolation":false,"InspectionDate":"2014-09-23 11:43:00","ProviderID":36006,"AgencyID":0},{"InspectionID":333127,"HasViolation":false,"InspectionDate":"2015-01-26 09:53:00","ProviderID":36006,"AgencyID":0},{"InspectionID":338472,"HasViolation":false,"InspectionDate":"2015-09-22 11:55:00","ProviderID":36006,"AgencyID":0},{"InspectionID":353279,"HasViolation":false,"InspectionDate":"2016-01-27 08:10:00","ProviderID":36006,"AgencyID":0},{"InspectionID":363061,"HasViolation":false,"InspectionDate":"2016-05-09 13:50:00","ProviderID":36006,"AgencyID":0},{"InspectionID":377235,"HasViolation":false,"InspectionDate":"2016-09-26 08:40:00","ProviderID":36006,"AgencyID":0},{"InspectionID":387788,"HasViolation":false,"InspectionDate":"2017-01-23 15:20:00","ProviderID":36006,"AgencyID":0},{"InspectionID":398924,"HasViolation":false,"InspectionDate":"2017-04-28 11:45:00","ProviderID":36006,"AgencyID":0}],"VPKAccreditation":[],"VPKClass":[],"VPKCurriculum":[]},"reportIDs":null,"_displayDistance":true,"Inspections":[{"InspectionID":398924,"HasViolation":false,"InspectionDate":"2017-04-28 11:45:00","ProviderID":36006,"AgencyID":0},{"InspectionID":387788,"HasViolation":false,"InspectionDate":"2017-01-23 15:20:00","ProviderID":36006,"AgencyID":0},{"InspectionID":377235,"HasViolation":false,"InspectionDate":"2016-09-26 08:40:00","ProviderID":36006,"AgencyID":0},{"InspectionID":363061,"HasViolation":false,"InspectionDate":"2016-05-09 13:50:00","ProviderID":36006,"AgencyID":0},{"InspectionID":353279,"HasViolation":false,"InspectionDate":"2016-01-27 08:10:00","ProviderID":36006,"AgencyID":0},{"InspectionID":338472,"HasViolation":false,"InspectionDate":"2015-09-22 11:55:00","ProviderID":36006,"AgencyID":0},{"InspectionID":305269,"HasViolation":false,"InspectionDate":"2015-06-08 09:38:00","ProviderID":36006,"AgencyID":0},{"InspectionID":296905,"HasViolation":true,"InspectionDate":"2015-05-05 13:05:00","ProviderID":36006,"AgencyID":0},{"InspectionID":333127,"HasViolation":false,"InspectionDate":"2015-01-26 09:53:00","ProviderID":36006,"AgencyID":0},{"InspectionID":310773,"HasViolation":false,"InspectionDate":"2014-09-23 11:43:00","ProviderID":36006,"AgencyID":0}],"VPKAccreditation":[],"VPKClass":[],"VPKCurriculum":[],"Distance":"1.35 miles","DisplayServices":{"After School":1,"Before School":1,"Drop In":1,"Food Served":1,"Full Day":1,"Half Day":1,"Open Year-Round":1}},{"_distance":9999,"Provider":{"ProviderNumber":"R01OK2067 ","Name":"Hill Family Day Care Home","Capacity":10,"LicenseExpirationDate":"08/19/2017","IsReligiousExempt":false,"IsFaithBased":false,"IsHeadStart":false,"IsOfferingSchoolReadiness":false,"IsPublicSchool":false,"OriginationDate":"08/19/2013","ProviderID":30227,"AddressID":5518,"StreetNumber":"85","StreetPreDirection":null,"StreetName":"Binnacle","StreetSuffix":"Ln","StreetPostDirection":null,"SecondaryDesignatorPrefix":null,"SecondaryDesignatorSuffix":null,"ExtraSecondaryDesignatorPrefix":null,"ExtraSecondaryDesignatorSuffix":null,"City":"Shalimar","County":"Okaloosa","State":"FL","ZipCode":"32579","ZipPlus4":"1455","Latitude":30.447463,"Longitude":-86.569101,"DisplayAddressOnWeb":false,"PhoneNumber":8502407850,"DisplayPhoneOnWeb":true,"ProgramType":"Family Day Care Home","Status":"Active","Services":"Drop In;Food Served;Full Day;Infant Care;Open Year-Round","FullAddress":"85 Binnacle Ln, Shalimar FL 32579-1455","GoldSealAccreditingAgency":null,"GoldSealEffectiveDate":null,"GoldSealExpirationDate":null,"GoldSealStatusID":null,"MondayHours":" 6:00AM to 4:30PM","TuesdayHours":" 6:00AM to 4:30PM","WednesdayHours":" 6:00AM to 4:30PM","ThursdayHours":" 6:00AM to 4:30PM","FridayHours":" 6:00AM to 4:30PM","SaturdayHours":null,"SundayHours":null,"LicenseStatus":"Registered","DBAName":null,"IsVPK":false,"VpkStatusID":1,"AgencyID":2,"AlternateProviderNumber":null,"Inspections":[],"VPKAccreditation":[],"VPKClass":[],"VPKCurriculum":[]},"reportIDs":null,"_displayDistance":false,"Inspections":[],"VPKAccreditation":[],"VPKClass":[],"VPKCurriculum":[],"Distance":"N/A","DisplayServices":{"Drop In":1,"Food Served":1,"Full Day":1,"Infant Care":1,"Open Year-Round":1}},{"_distance":9999,"Provider":{"ProviderNumber":"R01OK0115 ","Name":"Ruggs Family Day Care Home","Capacity":10,"LicenseExpirationDate":"01/31/2018","IsReligiousExempt":false,"IsFaithBased":false,"IsHeadStart":false,"IsOfferingSchoolReadiness":true,"IsPublicSchool":false,"OriginationDate":"02/22/1995","ProviderID":32758,"AddressID":17773,"StreetNumber":"17","StreetPreDirection":null,"StreetName":"Berwick","StreetSuffix":"Cir","StreetPostDirection":null,"SecondaryDesignatorPrefix":null,"SecondaryDesignatorSuffix":null,"ExtraSecondaryDesignatorPrefix":null,"ExtraSecondaryDesignatorSuffix":null,"City":"Shalimar","County":"Okaloosa","State":"FL","ZipCode":"32579","ZipPlus4":"2021","Latitude":30.438400,"Longitude":-86.566070,"DisplayAddressOnWeb":false,"PhoneNumber":8506518350,"DisplayPhoneOnWeb":true,"ProgramType":"Family Day Care Home","Status":"Active","Services":"After School;Before School;Drop In;Food Served;Full Day;Infant Care;Open Year-Round","FullAddress":"17 Berwick Cir, Shalimar FL 32579-2021","GoldSealAccreditingAgency":null,"GoldSealEffectiveDate":null,"GoldSealExpirationDate":null,"GoldSealStatusID":null,"MondayHours":" 6:30AM to 5:00PM","TuesdayHours":" 6:30AM to 5:00PM","WednesdayHours":" 6:30AM to 5:00PM","ThursdayHours":" 6:30AM to 5:00PM","FridayHours":" 6:30AM to 5:00PM","SaturdayHours":null,"SundayHours":null,"LicenseStatus":"Registered","DBAName":null,"IsVPK":false,"VpkStatusID":1,"AgencyID":2,"AlternateProviderNumber":null,"Inspections":[],"VPKAccreditation":[],"VPKClass":[],"VPKCurriculum":[]},"reportIDs":null,"_displayDistance":false,"Inspections":[],"VPKAccreditation":[],"VPKClass":[],"VPKCurriculum":[],"Distance":"N/A","DisplayServices":{"After School":1,"Before School":1,"Drop In":1,"Food Served":1,"Full Day":1,"Infant Care":1,"Open Year-Round":1}}]