[{"_distance":1.63488017098436,"Provider":{"ProviderNumber":"C08AL0286 ","Name":"Lee\u0027s Preschool Center Inc","Capacity":75,"LicenseExpirationDate":"06/01/2018","IsReligiousExempt":false,"IsFaithBased":false,"IsHeadStart":false,"IsOfferingSchoolReadiness":true,"IsPublicSchool":false,"OriginationDate":"02/01/1975","ProviderID":35323,"AddressID":22578,"StreetNumber":"14017","StreetPreDirection":"NW","StreetName":"166th","StreetSuffix":"Pl","StreetPostDirection":null,"SecondaryDesignatorPrefix":null,"SecondaryDesignatorSuffix":null,"ExtraSecondaryDesignatorPrefix":null,"ExtraSecondaryDesignatorSuffix":null,"City":"Alachua","County":"Alachua","State":"FL","ZipCode":"32615","ZipPlus4":"4825","Latitude":29.806740,"Longitude":-82.495290,"DisplayAddressOnWeb":true,"PhoneNumber":3864622109,"DisplayPhoneOnWeb":true,"ProgramType":"Child Care Facility","Status":"Regular/Annual","Services":"After School;Before School;Drop In;Food Served;Full Day;Half Day;Infant Care;Open Year-Round;Transportation","FullAddress":"14017 NW 166th Pl, Alachua FL 32615-4825","GoldSealAccreditingAgency":null,"GoldSealEffectiveDate":null,"GoldSealExpirationDate":null,"GoldSealStatusID":null,"MondayHours":" 6:30AM to 6:00PM","TuesdayHours":" 6:30AM to 6:00PM","WednesdayHours":" 6:30AM to 6:00PM","ThursdayHours":" 6:30AM to 6:00PM","FridayHours":" 6:30AM to 6:00PM","SaturdayHours":null,"SundayHours":null,"LicenseStatus":"Licensed","DBAName":null,"IsVPK":true,"VpkStatusID":2,"AgencyID":2,"AlternateProviderNumber":null,"Inspections":[{"InspectionID":274406,"HasViolation":false,"InspectionDate":"2015-02-16 15:22:00","ProviderID":35323,"AgencyID":0},{"InspectionID":278158,"HasViolation":true,"InspectionDate":"2015-05-01 10:57:00","ProviderID":35323,"AgencyID":0},{"InspectionID":293075,"HasViolation":true,"InspectionDate":"2014-10-23 12:00:00","ProviderID":35323,"AgencyID":0},{"InspectionID":310219,"HasViolation":true,"InspectionDate":"2015-01-21 12:45:00","ProviderID":35323,"AgencyID":0},{"InspectionID":333353,"HasViolation":true,"InspectionDate":"2014-09-16 10:10:00","ProviderID":35323,"AgencyID":0},{"InspectionID":335227,"HasViolation":true,"InspectionDate":"2015-08-21 08:30:00","ProviderID":35323,"AgencyID":0},{"InspectionID":347041,"HasViolation":true,"InspectionDate":"2015-10-14 14:12:00","ProviderID":35323,"AgencyID":0},{"InspectionID":347960,"HasViolation":true,"InspectionDate":"2015-12-21 11:50:00","ProviderID":35323,"AgencyID":0},{"InspectionID":350735,"HasViolation":false,"InspectionDate":"2016-01-07 09:45:00","ProviderID":35323,"AgencyID":0},{"InspectionID":362075,"HasViolation":true,"InspectionDate":"2016-04-28 09:40:00","ProviderID":35323,"AgencyID":0},{"InspectionID":363283,"HasViolation":false,"InspectionDate":"2016-05-12 11:55:00","ProviderID":35323,"AgencyID":0},{"InspectionID":376543,"HasViolation":true,"InspectionDate":"2016-09-19 09:30:00","ProviderID":35323,"AgencyID":0},{"InspectionID":378072,"HasViolation":false,"InspectionDate":"2016-10-10 15:52:00","ProviderID":35323,"AgencyID":0},{"InspectionID":385698,"HasViolation":true,"InspectionDate":"2017-01-09 11:10:00","ProviderID":35323,"AgencyID":0},{"InspectionID":387517,"HasViolation":false,"InspectionDate":"2017-01-19 13:30:00","ProviderID":35323,"AgencyID":0},{"InspectionID":399276,"HasViolation":true,"InspectionDate":"2017-05-01 09:55:00","ProviderID":35323,"AgencyID":0}],"VPKAccreditation":[],"VPKClass":[{"ID":"afcbb478-2966-4c8c-b298-ebbe9f4d62f2","ProviderID":35323,"ClassRoomCode":"P1","ClassType":"540","StartDate":"08/22/2016","EndDate":"05/27/2017","Monday":"9:00AM to 12:00PM","Tuesday":"9:00AM to 12:00PM","Wednesday":"9:00AM to 12:00PM","Thursday":"9:00AM to 12:00PM","Friday":"9:00AM to 12:00PM","Saturday":null,"Sunday":null,"ClassRoomCount":1,"Capacity":20,"Enrollments":14,"InstructorCredential":"National Early Childhood Certificate","AgencyID":2}],"VPKCurriculum":[{"ID":"89472c63-6ebe-4d43-9fb8-dfcc20c9bdf6","ProviderID":35323,"Description":"LEARN EVERY","PublisherName":null}]},"reportIDs":null,"_displayDistance":true,"Inspections":[{"InspectionID":399276,"HasViolation":true,"InspectionDate":"2017-05-01 09:55:00","ProviderID":35323,"AgencyID":0},{"InspectionID":387517,"HasViolation":false,"InspectionDate":"2017-01-19 13:30:00","ProviderID":35323,"AgencyID":0},{"InspectionID":385698,"HasViolation":true,"InspectionDate":"2017-01-09 11:10:00","ProviderID":35323,"AgencyID":0},{"InspectionID":378072,"HasViolation":false,"InspectionDate":"2016-10-10 15:52:00","ProviderID":35323,"AgencyID":0},{"InspectionID":376543,"HasViolation":true,"InspectionDate":"2016-09-19 09:30:00","ProviderID":35323,"AgencyID":0},{"InspectionID":363283,"HasViolation":false,"InspectionDate":"2016-05-12 11:55:00","ProviderID":35323,"AgencyID":0},{"InspectionID":362075,"HasViolation":true,"InspectionDate":"2016-04-28 09:40:00","ProviderID":35323,"AgencyID":0},{"InspectionID":350735,"HasViolation":false,"InspectionDate":"2016-01-07 09:45:00","ProviderID":35323,"AgencyID":0},{"InspectionID":347960,"HasViolation":true,"InspectionDate":"2015-12-21 11:50:00","ProviderID":35323,"AgencyID":0},{"InspectionID":347041,"HasViolation":true,"InspectionDate":"2015-10-14 14:12:00","ProviderID":35323,"AgencyID":0},{"InspectionID":335227,"HasViolation":true,"InspectionDate":"2015-08-21 08:30:00","ProviderID":35323,"AgencyID":0},{"InspectionID":278158,"HasViolation":true,"InspectionDate":"2015-05-01 10:57:00","ProviderID":35323,"AgencyID":0},{"InspectionID":274406,"HasViolation":false,"InspectionDate":"2015-02-16 15:22:00","ProviderID":35323,"AgencyID":0},{"InspectionID":310219,"HasViolation":true,"InspectionDate":"2015-01-21 12:45:00","ProviderID":35323,"AgencyID":0},{"InspectionID":293075,"HasViolation":true,"InspectionDate":"2014-10-23 12:00:00","ProviderID":35323,"AgencyID":0},{"InspectionID":333353,"HasViolation":true,"InspectionDate":"2014-09-16 10:10:00","ProviderID":35323,"AgencyID":0}],"VPKAccreditation":[],"VPKClass":[{"ID":"afcbb478-2966-4c8c-b298-ebbe9f4d62f2","ProviderID":35323,"ClassRoomCode":"P1","ClassType":"540","StartDate":"08/22/2016","EndDate":"05/27/2017","Monday":"9:00AM to 12:00PM","Tuesday":"9:00AM to 12:00PM","Wednesday":"9:00AM to 12:00PM","Thursday":"9:00AM to 12:00PM","Friday":"9:00AM to 12:00PM","Saturday":null,"Sunday":null,"ClassRoomCount":1,"Capacity":20,"Enrollments":14,"InstructorCredential":"National Early Childhood Certificate","AgencyID":2}],"VPKCurriculum":[{"ID":"89472c63-6ebe-4d43-9fb8-dfcc20c9bdf6","ProviderID":35323,"Description":"LEARN EVERY","PublisherName":null}],"Distance":"1.63 miles","DisplayServices":{"After School":1,"Before School":1,"Drop In":1,"Food Served":1,"Full Day":1,"Half Day":1,"Infant Care":1,"Open Year-Round":1,"Transportation":1}},{"_distance":2.15121821429888,"Provider":{"ProviderNumber":"C08AL0185 ","Name":"Bhaktivedanta  Academy","Capacity":29,"LicenseExpirationDate":"03/30/2018","IsReligiousExempt":false,"IsFaithBased":false,"IsHeadStart":false,"IsOfferingSchoolReadiness":true,"IsPublicSchool":false,"OriginationDate":"08/24/2007","ProviderID":33847,"AddressID":12378,"StreetNumber":"17414","StreetPreDirection":"NW","StreetName":"112th","StreetSuffix":"Blvd","StreetPostDirection":null,"SecondaryDesignatorPrefix":null,"SecondaryDesignatorSuffix":null,"ExtraSecondaryDesignatorPrefix":null,"ExtraSecondaryDesignatorSuffix":null,"City":"Alachua","County":"Alachua","State":"FL","ZipCode":"32615","ZipPlus4":"4521","Latitude":29.814100,"Longitude":-82.466342,"DisplayAddressOnWeb":true,"PhoneNumber":3864622886,"DisplayPhoneOnWeb":true,"ProgramType":"Child Care Facility","Status":"Regular/Annual","Services":"After School;Full Day;Half Day;Open Year-Round","FullAddress":"17414 NW 112th Blvd, Alachua FL 32615-4521","GoldSealAccreditingAgency":null,"GoldSealEffectiveDate":null,"GoldSealExpirationDate":null,"GoldSealStatusID":null,"MondayHours":" 8:00AM to 6:00PM","TuesdayHours":" 8:00AM to 6:00PM","WednesdayHours":" 8:00AM to 6:00PM","ThursdayHours":" 8:00AM to 6:00PM","FridayHours":" 8:00AM to 6:00PM","SaturdayHours":null,"SundayHours":null,"LicenseStatus":"Licensed","DBAName":null,"IsVPK":true,"VpkStatusID":2,"AgencyID":2,"AlternateProviderNumber":null,"Inspections":[{"InspectionID":259275,"HasViolation":false,"InspectionDate":"2015-06-23 11:44:00","ProviderID":33847,"AgencyID":0},{"InspectionID":265263,"HasViolation":false,"InspectionDate":"2014-11-17 08:25:00","ProviderID":33847,"AgencyID":0},{"InspectionID":273895,"HasViolation":true,"InspectionDate":"2015-02-25 13:06:00","ProviderID":33847,"AgencyID":0},{"InspectionID":277304,"HasViolation":true,"InspectionDate":"2014-11-14 10:40:00","ProviderID":33847,"AgencyID":0},{"InspectionID":282941,"HasViolation":false,"InspectionDate":"2015-02-26 12:28:00","ProviderID":33847,"AgencyID":0},{"InspectionID":328980,"HasViolation":false,"InspectionDate":"2014-07-10 11:35:00","ProviderID":33847,"AgencyID":0},{"InspectionID":342591,"HasViolation":true,"InspectionDate":"2015-10-23 08:30:00","ProviderID":33847,"AgencyID":0},{"InspectionID":343059,"HasViolation":false,"InspectionDate":"2015-10-30 11:51:00","ProviderID":33847,"AgencyID":0},{"InspectionID":357004,"HasViolation":false,"InspectionDate":"2016-03-04 12:50:00","ProviderID":33847,"AgencyID":0},{"InspectionID":368828,"HasViolation":false,"InspectionDate":"2016-07-13 13:05:00","ProviderID":33847,"AgencyID":0},{"InspectionID":379922,"HasViolation":true,"InspectionDate":"2016-10-19 11:40:00","ProviderID":33847,"AgencyID":0},{"InspectionID":381916,"HasViolation":false,"InspectionDate":"2016-11-15 08:10:00","ProviderID":33847,"AgencyID":0},{"InspectionID":389796,"HasViolation":false,"InspectionDate":"2017-02-15 09:15:00","ProviderID":33847,"AgencyID":0}],"VPKAccreditation":[],"VPKClass":[{"ID":"bbd797d1-85e3-4818-9ff3-ddcffc650dda","ProviderID":33847,"ClassRoomCode":"P1","ClassType":"540","StartDate":"08/15/2016","EndDate":"06/01/2017","Monday":"8:00AM to 11:45AM","Tuesday":"8:00AM to 11:45AM","Wednesday":"8:00AM to 11:45AM","Thursday":"8:00AM to 11:45AM","Friday":null,"Saturday":null,"Sunday":null,"ClassRoomCount":1,"Capacity":20,"Enrollments":11,"InstructorCredential":"National Early Childhood Certificate","AgencyID":2}],"VPKCurriculum":[{"ID":"4517f31a-9f24-4115-a7b2-c263a648c46d","ProviderID":33847,"Description":"Montessori","PublisherName":null}]},"reportIDs":null,"_displayDistance":true,"Inspections":[{"InspectionID":389796,"HasViolation":false,"InspectionDate":"2017-02-15 09:15:00","ProviderID":33847,"AgencyID":0},{"InspectionID":381916,"HasViolation":false,"InspectionDate":"2016-11-15 08:10:00","ProviderID":33847,"AgencyID":0},{"InspectionID":379922,"HasViolation":true,"InspectionDate":"2016-10-19 11:40:00","ProviderID":33847,"AgencyID":0},{"InspectionID":368828,"HasViolation":false,"InspectionDate":"2016-07-13 13:05:00","ProviderID":33847,"AgencyID":0},{"InspectionID":357004,"HasViolation":false,"InspectionDate":"2016-03-04 12:50:00","ProviderID":33847,"AgencyID":0},{"InspectionID":343059,"HasViolation":false,"InspectionDate":"2015-10-30 11:51:00","ProviderID":33847,"AgencyID":0},{"InspectionID":342591,"HasViolation":true,"InspectionDate":"2015-10-23 08:30:00","ProviderID":33847,"AgencyID":0},{"InspectionID":259275,"HasViolation":false,"InspectionDate":"2015-06-23 11:44:00","ProviderID":33847,"AgencyID":0},{"InspectionID":282941,"HasViolation":false,"InspectionDate":"2015-02-26 12:28:00","ProviderID":33847,"AgencyID":0},{"InspectionID":273895,"HasViolation":true,"InspectionDate":"2015-02-25 13:06:00","ProviderID":33847,"AgencyID":0},{"InspectionID":265263,"HasViolation":false,"InspectionDate":"2014-11-17 08:25:00","ProviderID":33847,"AgencyID":0},{"InspectionID":277304,"HasViolation":true,"InspectionDate":"2014-11-14 10:40:00","ProviderID":33847,"AgencyID":0},{"InspectionID":328980,"HasViolation":false,"InspectionDate":"2014-07-10 11:35:00","ProviderID":33847,"AgencyID":0}],"VPKAccreditation":[],"VPKClass":[{"ID":"bbd797d1-85e3-4818-9ff3-ddcffc650dda","ProviderID":33847,"ClassRoomCode":"P1","ClassType":"540","StartDate":"08/15/2016","EndDate":"06/01/2017","Monday":"8:00AM to 11:45AM","Tuesday":"8:00AM to 11:45AM","Wednesday":"8:00AM to 11:45AM","Thursday":"8:00AM to 11:45AM","Friday":null,"Saturday":null,"Sunday":null,"ClassRoomCount":1,"Capacity":20,"Enrollments":11,"InstructorCredential":"National Early Childhood Certificate","AgencyID":2}],"VPKCurriculum":[{"ID":"4517f31a-9f24-4115-a7b2-c263a648c46d","ProviderID":33847,"Description":"Montessori","PublisherName":null}],"Distance":"2.15 miles","DisplayServices":{"After School":1,"Full Day":1,"Half Day":1,"Open Year-Round":1}},{"_distance":2.36172618437474,"Provider":{"ProviderNumber":"E08AL0079 ","Name":"Attentive Child Care","Capacity":12,"LicenseExpirationDate":null,"IsReligiousExempt":null,"IsFaithBased":null,"IsHeadStart":false,"IsOfferingSchoolReadiness":false,"IsPublicSchool":null,"OriginationDate":null,"ProviderID":17722,"AddressID":1967,"StreetNumber":"16717","StreetPreDirection":"NW","StreetName":"173rd","StreetSuffix":"Ter","StreetPostDirection":null,"SecondaryDesignatorPrefix":null,"SecondaryDesignatorSuffix":null,"ExtraSecondaryDesignatorPrefix":null,"ExtraSecondaryDesignatorSuffix":null,"City":"Alachua","County":"Alachua","State":"FL","ZipCode":"32615","ZipPlus4":"4727","Latitude":29.808452,"Longitude":-82.527160,"DisplayAddressOnWeb":true,"PhoneNumber":3864180595,"DisplayPhoneOnWeb":true,"ProgramType":"Non-Public School","Status":"Active","Services":"After School;Before School;Food Served;Full Day;Half Day","FullAddress":"16717 NW 173rd Ter, Alachua FL 32615-4727","GoldSealAccreditingAgency":null,"GoldSealEffectiveDate":null,"GoldSealExpirationDate":null,"GoldSealStatusID":null,"MondayHours":" 9:00AM to 6:00PM","TuesdayHours":" 9:00AM to 6:00PM","WednesdayHours":" 9:00AM to 6:00PM","ThursdayHours":" 9:00AM to 6:00PM","FridayHours":" 9:00AM to 6:00PM","SaturdayHours":null,"SundayHours":null,"LicenseStatus":"Exempt","DBAName":null,"IsVPK":false,"VpkStatusID":3,"AgencyID":2,"AlternateProviderNumber":null,"Inspections":[],"VPKAccreditation":[],"VPKClass":[],"VPKCurriculum":[]},"reportIDs":null,"_displayDistance":true,"Inspections":[],"VPKAccreditation":[],"VPKClass":[],"VPKCurriculum":[],"Distance":"2.36 miles","DisplayServices":{"After School":1,"Before School":1,"Food Served":1,"Full Day":1,"Half Day":1}},{"_distance":2.42880284692995,"Provider":{"ProviderNumber":"C08AL0072 ","Name":"O2B Kids College 6, Ltd","Capacity":208,"LicenseExpirationDate":"05/25/2018","IsReligiousExempt":false,"IsFaithBased":false,"IsHeadStart":false,"IsOfferingSchoolReadiness":true,"IsPublicSchool":false,"OriginationDate":"09/18/2006","ProviderID":36556,"AddressID":7664,"StreetNumber":"14400","StreetPreDirection":"NW","StreetName":"152nd","StreetSuffix":"Ln","StreetPostDirection":null,"SecondaryDesignatorPrefix":null,"SecondaryDesignatorSuffix":null,"ExtraSecondaryDesignatorPrefix":null,"ExtraSecondaryDesignatorSuffix":null,"City":"Alachua","County":"Alachua","State":"FL","ZipCode":"32615","ZipPlus4":"8606","Latitude":29.795231,"Longitude":-82.498232,"DisplayAddressOnWeb":true,"PhoneNumber":3864620092,"DisplayPhoneOnWeb":true,"ProgramType":"Child Care Facility","Status":"Regular/Annual","Services":"Food Served;Full Day;Half Day;Open Year-Round","FullAddress":"14400 NW 152nd Ln, Alachua FL 32615-8606","GoldSealAccreditingAgency":"National Accreditation Commission","GoldSealEffectiveDate":"09/26/2014","GoldSealExpirationDate":"09/26/2017","GoldSealStatusID":1,"MondayHours":" 6:30AM to 6:30PM","TuesdayHours":" 6:30AM to 6:30PM","WednesdayHours":" 6:30AM to 6:30PM","ThursdayHours":" 6:30AM to 6:30PM","FridayHours":" 6:30AM to 6:30PM","SaturdayHours":null,"SundayHours":null,"LicenseStatus":"Licensed","DBAName":null,"IsVPK":true,"VpkStatusID":2,"AgencyID":2,"AlternateProviderNumber":null,"Inspections":[{"InspectionID":298943,"HasViolation":true,"InspectionDate":"2014-09-10 08:50:00","ProviderID":36556,"AgencyID":0},{"InspectionID":310556,"HasViolation":true,"InspectionDate":"2015-04-24 08:30:00","ProviderID":36556,"AgencyID":0},{"InspectionID":332871,"HasViolation":false,"InspectionDate":"2015-01-16 08:40:00","ProviderID":36556,"AgencyID":0},{"InspectionID":335229,"HasViolation":false,"InspectionDate":"2015-08-21 10:11:00","ProviderID":36556,"AgencyID":0},{"InspectionID":347434,"HasViolation":false,"InspectionDate":"2015-12-16 08:50:00","ProviderID":36556,"AgencyID":0},{"InspectionID":361693,"HasViolation":false,"InspectionDate":"2016-04-21 10:00:00","ProviderID":36556,"AgencyID":0},{"InspectionID":374973,"HasViolation":true,"InspectionDate":"2016-09-09 07:45:00","ProviderID":36556,"AgencyID":0},{"InspectionID":377558,"HasViolation":false,"InspectionDate":"2016-09-29 16:45:00","ProviderID":36556,"AgencyID":0},{"InspectionID":385699,"HasViolation":false,"InspectionDate":"2017-01-09 14:10:00","ProviderID":36556,"AgencyID":0},{"InspectionID":394553,"HasViolation":true,"InspectionDate":"2017-01-23 15:11:00","ProviderID":36556,"AgencyID":0},{"InspectionID":397874,"HasViolation":true,"InspectionDate":"2017-04-19 09:58:00","ProviderID":36556,"AgencyID":0},{"InspectionID":400052,"HasViolation":false,"InspectionDate":"2017-05-09 08:27:00","ProviderID":36556,"AgencyID":0}],"VPKAccreditation":[{"ID":"efbdf018-366f-4c2e-94cc-f3353df182af","ProviderID":36556,"Name":"National Accreditation Commission","EffectiveDate":"10/03/2014","ExpirationDate":"10/03/2017","AgencyID":2}],"VPKClass":[{"ID":"95eba05f-96d1-43ed-89da-9a4df7c102e0","ProviderID":36556,"ClassRoomCode":"P1","ClassType":"540","StartDate":"08/15/2016","EndDate":"06/03/2017","Monday":"9:00AM to 12:00PM","Tuesday":"9:00AM to 12:00PM","Wednesday":"9:00AM to 12:00PM","Thursday":"9:00AM to 12:00PM","Friday":"9:00AM to 12:00PM","Saturday":null,"Sunday":null,"ClassRoomCount":1,"Capacity":20,"Enrollments":20,"InstructorCredential":"Florida Equivalent Credential: FCCPC/ECPC/CCAC/CDAE","AgencyID":2},{"ID":"e3c7f08b-ed2a-4d39-81f5-0d2185be3cb8","ProviderID":36556,"ClassRoomCode":"P2","ClassType":"540","StartDate":"08/15/2016","EndDate":"06/03/2017","Monday":"9:00AM to 12:00PM","Tuesday":"9:00AM to 12:00PM","Wednesday":"9:00AM to 12:00PM","Thursday":"9:00AM to 12:00PM","Friday":"9:00AM to 12:00PM","Saturday":null,"Sunday":null,"ClassRoomCount":1,"Capacity":20,"Enrollments":18,"InstructorCredential":"Florida Equivalent Credential: FCCPC/ECPC/CCAC/CDAE","AgencyID":2},{"ID":"0b8f1adf-887c-4f2a-9f57-605401043909","ProviderID":36556,"ClassRoomCode":"P3","ClassType":"540","StartDate":"08/15/2016","EndDate":"06/03/2017","Monday":"9:00AM to 12:00PM","Tuesday":"9:00AM to 12:00PM","Wednesday":"9:00AM to 12:00PM","Thursday":"9:00AM to 12:00PM","Friday":"9:00AM to 12:00PM","Saturday":null,"Sunday":null,"ClassRoomCount":1,"Capacity":20,"Enrollments":17,"InstructorCredential":"Master\u0027s Degree","AgencyID":2},{"ID":"ec2abe04-dcd3-41ee-8686-b3e9eba5c1de","ProviderID":36556,"ClassRoomCode":"P4","ClassType":"540","StartDate":"08/15/2016","EndDate":"06/03/2017","Monday":"9:00AM to 12:00PM","Tuesday":"9:00AM to 12:00PM","Wednesday":"9:00AM to 12:00PM","Thursday":"9:00AM to 12:00PM","Friday":"9:00AM to 12:00PM","Saturday":null,"Sunday":null,"ClassRoomCount":1,"Capacity":20,"Enrollments":0,"InstructorCredential":"Florida Equivalent Credential: FCCPC/ECPC/CCAC/CDAE","AgencyID":2}],"VPKCurriculum":[{"ID":"43bed813-b5b9-43fb-8887-3efd9b23f720","ProviderID":36556,"Description":"BABY DOLL CIRCLE TIME","PublisherName":null},{"ID":"85cd7f4b-97fa-43e2-b349-65e0531cceb6","ProviderID":36556,"Description":"O2B KIDS","PublisherName":null}]},"reportIDs":null,"_displayDistance":true,"Inspections":[{"InspectionID":400052,"HasViolation":false,"InspectionDate":"2017-05-09 08:27:00","ProviderID":36556,"AgencyID":0},{"InspectionID":397874,"HasViolation":true,"InspectionDate":"2017-04-19 09:58:00","ProviderID":36556,"AgencyID":0},{"InspectionID":394553,"HasViolation":true,"InspectionDate":"2017-01-23 15:11:00","ProviderID":36556,"AgencyID":0},{"InspectionID":385699,"HasViolation":false,"InspectionDate":"2017-01-09 14:10:00","ProviderID":36556,"AgencyID":0},{"InspectionID":377558,"HasViolation":false,"InspectionDate":"2016-09-29 16:45:00","ProviderID":36556,"AgencyID":0},{"InspectionID":374973,"HasViolation":true,"InspectionDate":"2016-09-09 07:45:00","ProviderID":36556,"AgencyID":0},{"InspectionID":361693,"HasViolation":false,"InspectionDate":"2016-04-21 10:00:00","ProviderID":36556,"AgencyID":0},{"InspectionID":347434,"HasViolation":false,"InspectionDate":"2015-12-16 08:50:00","ProviderID":36556,"AgencyID":0},{"InspectionID":335229,"HasViolation":false,"InspectionDate":"2015-08-21 10:11:00","ProviderID":36556,"AgencyID":0},{"InspectionID":310556,"HasViolation":true,"InspectionDate":"2015-04-24 08:30:00","ProviderID":36556,"AgencyID":0},{"InspectionID":332871,"HasViolation":false,"InspectionDate":"2015-01-16 08:40:00","ProviderID":36556,"AgencyID":0},{"InspectionID":298943,"HasViolation":true,"InspectionDate":"2014-09-10 08:50:00","ProviderID":36556,"AgencyID":0}],"VPKAccreditation":[{"ID":"efbdf018-366f-4c2e-94cc-f3353df182af","ProviderID":36556,"Name":"National Accreditation Commission","EffectiveDate":"10/03/2014","ExpirationDate":"10/03/2017","AgencyID":2}],"VPKClass":[{"ID":"95eba05f-96d1-43ed-89da-9a4df7c102e0","ProviderID":36556,"ClassRoomCode":"P1","ClassType":"540","StartDate":"08/15/2016","EndDate":"06/03/2017","Monday":"9:00AM to 12:00PM","Tuesday":"9:00AM to 12:00PM","Wednesday":"9:00AM to 12:00PM","Thursday":"9:00AM to 12:00PM","Friday":"9:00AM to 12:00PM","Saturday":null,"Sunday":null,"ClassRoomCount":1,"Capacity":20,"Enrollments":20,"InstructorCredential":"Florida Equivalent Credential: FCCPC/ECPC/CCAC/CDAE","AgencyID":2},{"ID":"e3c7f08b-ed2a-4d39-81f5-0d2185be3cb8","ProviderID":36556,"ClassRoomCode":"P2","ClassType":"540","StartDate":"08/15/2016","EndDate":"06/03/2017","Monday":"9:00AM to 12:00PM","Tuesday":"9:00AM to 12:00PM","Wednesday":"9:00AM to 12:00PM","Thursday":"9:00AM to 12:00PM","Friday":"9:00AM to 12:00PM","Saturday":null,"Sunday":null,"ClassRoomCount":1,"Capacity":20,"Enrollments":18,"InstructorCredential":"Florida Equivalent Credential: FCCPC/ECPC/CCAC/CDAE","AgencyID":2},{"ID":"0b8f1adf-887c-4f2a-9f57-605401043909","ProviderID":36556,"ClassRoomCode":"P3","ClassType":"540","StartDate":"08/15/2016","EndDate":"06/03/2017","Monday":"9:00AM to 12:00PM","Tuesday":"9:00AM to 12:00PM","Wednesday":"9:00AM to 12:00PM","Thursday":"9:00AM to 12:00PM","Friday":"9:00AM to 12:00PM","Saturday":null,"Sunday":null,"ClassRoomCount":1,"Capacity":20,"Enrollments":17,"InstructorCredential":"Master\u0027s Degree","AgencyID":2},{"ID":"ec2abe04-dcd3-41ee-8686-b3e9eba5c1de","ProviderID":36556,"ClassRoomCode":"P4","ClassType":"540","StartDate":"08/15/2016","EndDate":"06/03/2017","Monday":"9:00AM to 12:00PM","Tuesday":"9:00AM to 12:00PM","Wednesday":"9:00AM to 12:00PM","Thursday":"9:00AM to 12:00PM","Friday":"9:00AM to 12:00PM","Saturday":null,"Sunday":null,"ClassRoomCount":1,"Capacity":20,"Enrollments":0,"InstructorCredential":"Florida Equivalent Credential: FCCPC/ECPC/CCAC/CDAE","AgencyID":2}],"VPKCurriculum":[{"ID":"43bed813-b5b9-43fb-8887-3efd9b23f720","ProviderID":36556,"Description":"BABY DOLL CIRCLE TIME","PublisherName":null},{"ID":"85cd7f4b-97fa-43e2-b349-65e0531cceb6","ProviderID":36556,"Description":"O2B KIDS","PublisherName":null}],"Distance":"2.43 miles","DisplayServices":{"Food Served":1,"Full Day":1,"Half Day":1,"Open Year-Round":1}},{"_distance":2.64779786119198,"Provider":{"ProviderNumber":"E08AL0078 ","Name":"Alachua Learning Center","Capacity":95,"LicenseExpirationDate":null,"IsReligiousExempt":false,"IsFaithBased":false,"IsHeadStart":false,"IsOfferingSchoolReadiness":true,"IsPublicSchool":false,"OriginationDate":null,"ProviderID":291177,"AddressID":40558,"StreetNumber":"11100","StreetPreDirection":"W ","StreetName":"State Road 235","StreetSuffix":null,"StreetPostDirection":null,"SecondaryDesignatorPrefix":null,"SecondaryDesignatorSuffix":null,"ExtraSecondaryDesignatorPrefix":null,"ExtraSecondaryDesignatorSuffix":null,"City":"Alachua","County":"Alachua","State":"FL","ZipCode":"32615","ZipPlus4":"4965","Latitude":29.800000,"Longitude":-82.470000,"DisplayAddressOnWeb":true,"PhoneNumber":3864182080,"DisplayPhoneOnWeb":true,"ProgramType":"Non-Public School","Status":"Active","Services":"After School;Drop In;Food Served;School Year Only","FullAddress":"11100 W State Road 235, Alachua FL, 32615","GoldSealAccreditingAgency":null,"GoldSealEffectiveDate":null,"GoldSealExpirationDate":null,"GoldSealStatusID":null,"MondayHours":" 1:50PM to 6:00PM","TuesdayHours":" 1:50PM to 6:00PM","WednesdayHours":" 1:50PM to 6:00PM","ThursdayHours":" 1:50PM to 6:00PM","FridayHours":" 1:50PM to 6:00PM","SaturdayHours":null,"SundayHours":null,"LicenseStatus":"Exempt","DBAName":null,"IsVPK":false,"VpkStatusID":1,"AgencyID":2,"AlternateProviderNumber":null,"Inspections":[{"InspectionID":387508,"HasViolation":false,"InspectionDate":"2017-01-19 11:00:00","ProviderID":291177,"AgencyID":0}],"VPKAccreditation":[],"VPKClass":[],"VPKCurriculum":[]},"reportIDs":null,"_displayDistance":true,"Inspections":[{"InspectionID":387508,"HasViolation":false,"InspectionDate":"2017-01-19 11:00:00","ProviderID":291177,"AgencyID":0}],"VPKAccreditation":[],"VPKClass":[],"VPKCurriculum":[],"Distance":"2.65 miles","DisplayServices":{"After School":1,"Drop In":1,"Food Served":1,"School Year Only":1}},{"_distance":2.66482593147927,"Provider":{"ProviderNumber":"E08AL0031 ","Name":"Alachua County Schools - Irby Elementary","Capacity":0,"LicenseExpirationDate":null,"IsReligiousExempt":false,"IsFaithBased":false,"IsHeadStart":false,"IsOfferingSchoolReadiness":false,"IsPublicSchool":false,"OriginationDate":null,"ProviderID":20866,"AddressID":14007,"StreetNumber":" ","StreetPreDirection":"NW","StreetName":"140th","StreetSuffix":"St","StreetPostDirection":null,"SecondaryDesignatorPrefix":null,"SecondaryDesignatorSuffix":null,"ExtraSecondaryDesignatorPrefix":null,"ExtraSecondaryDesignatorSuffix":null,"City":"Alachua","County":"Alachua","State":"FL","ZipCode":"32615","ZipPlus4":null,"Latitude":29.791800,"Longitude":-82.496590,"DisplayAddressOnWeb":true,"PhoneNumber":3524625002,"DisplayPhoneOnWeb":true,"ProgramType":"Public School","Status":"Active","Services":"Open Year-Round","FullAddress":"13505 Northeast 140th Street, Alachua FL 32615","GoldSealAccreditingAgency":"National Association for the Education of Young Children","GoldSealEffectiveDate":"06/27/2012","GoldSealExpirationDate":"12/01/2017","GoldSealStatusID":1,"MondayHours":null,"TuesdayHours":null,"WednesdayHours":null,"ThursdayHours":null,"FridayHours":null,"SaturdayHours":null,"SundayHours":null,"LicenseStatus":"Exempt","DBAName":null,"IsVPK":false,"VpkStatusID":1,"AgencyID":2,"AlternateProviderNumber":null,"Inspections":[{"InspectionID":387924,"HasViolation":true,"InspectionDate":"2017-01-25 13:05:00","ProviderID":20866,"AgencyID":0},{"InspectionID":394865,"HasViolation":true,"InspectionDate":"2017-03-28 14:30:00","ProviderID":20866,"AgencyID":0},{"InspectionID":399955,"HasViolation":true,"InspectionDate":"2017-05-08 12:30:00","ProviderID":20866,"AgencyID":0}],"VPKAccreditation":[],"VPKClass":[],"VPKCurriculum":[]},"reportIDs":null,"_displayDistance":true,"Inspections":[{"InspectionID":399955,"HasViolation":true,"InspectionDate":"2017-05-08 12:30:00","ProviderID":20866,"AgencyID":0},{"InspectionID":394865,"HasViolation":true,"InspectionDate":"2017-03-28 14:30:00","ProviderID":20866,"AgencyID":0},{"InspectionID":387924,"HasViolation":true,"InspectionDate":"2017-01-25 13:05:00","ProviderID":20866,"AgencyID":0}],"VPKAccreditation":[],"VPKClass":[],"VPKCurriculum":[],"Distance":"2.66 miles","DisplayServices":{"Open Year-Round":1}},{"_distance":2.90732978293071,"Provider":{"ProviderNumber":"C08AL0408 ","Name":"Little Angels Child Care \u0026 Learning Center","Capacity":34,"LicenseExpirationDate":"09/22/2017","IsReligiousExempt":false,"IsFaithBased":false,"IsHeadStart":false,"IsOfferingSchoolReadiness":false,"IsPublicSchool":false,"OriginationDate":"08/16/2000","ProviderID":31039,"AddressID":14372,"StreetNumber":"14821","StreetPreDirection":"NW","StreetName":"US Highway 441","StreetSuffix":null,"StreetPostDirection":null,"SecondaryDesignatorPrefix":null,"SecondaryDesignatorSuffix":null,"ExtraSecondaryDesignatorPrefix":null,"ExtraSecondaryDesignatorSuffix":null,"City":"Alachua","County":"Alachua","State":"FL","ZipCode":"32615","ZipPlus4":"8203","Latitude":29.789590,"Longitude":-82.484980,"DisplayAddressOnWeb":true,"PhoneNumber":3864182211,"DisplayPhoneOnWeb":true,"ProgramType":"Child Care Facility","Status":"Regular/Annual","Services":"After School;Drop In;Food Served;Full Day;Half Day;Infant Care;Open Year-Round","FullAddress":"14821 NW US Highway 441, Alachua FL 32615-8203","GoldSealAccreditingAgency":null,"GoldSealEffectiveDate":null,"GoldSealExpirationDate":null,"GoldSealStatusID":null,"MondayHours":" 6:30AM to 6:00PM","TuesdayHours":" 6:30AM to 6:00PM","WednesdayHours":" 6:30AM to 6:00PM","ThursdayHours":" 6:30AM to 6:00PM","FridayHours":" 6:30AM to 6:00PM","SaturdayHours":null,"SundayHours":null,"LicenseStatus":"Licensed","DBAName":null,"IsVPK":false,"VpkStatusID":1,"AgencyID":2,"AlternateProviderNumber":null,"Inspections":[{"InspectionID":273684,"HasViolation":true,"InspectionDate":"2014-09-05 10:30:00","ProviderID":31039,"AgencyID":0},{"InspectionID":277010,"HasViolation":false,"InspectionDate":"2015-01-21 15:28:00","ProviderID":31039,"AgencyID":0},{"InspectionID":290707,"HasViolation":true,"InspectionDate":"2015-01-16 10:00:00","ProviderID":31039,"AgencyID":0},{"InspectionID":298791,"HasViolation":false,"InspectionDate":"2015-04-23 11:55:00","ProviderID":31039,"AgencyID":0},{"InspectionID":320123,"HasViolation":true,"InspectionDate":"2015-04-16 13:00:00","ProviderID":31039,"AgencyID":0},{"InspectionID":324931,"HasViolation":false,"InspectionDate":"2014-09-19 14:58:00","ProviderID":31039,"AgencyID":0},{"InspectionID":334990,"HasViolation":true,"InspectionDate":"2015-08-19 08:19:00","ProviderID":31039,"AgencyID":0},{"InspectionID":347040,"HasViolation":true,"InspectionDate":"2015-12-10 13:08:00","ProviderID":31039,"AgencyID":0},{"InspectionID":356663,"HasViolation":true,"InspectionDate":"2016-02-16 13:00:00","ProviderID":31039,"AgencyID":0},{"InspectionID":361547,"HasViolation":true,"InspectionDate":"2016-04-15 10:25:00","ProviderID":31039,"AgencyID":0},{"InspectionID":363278,"HasViolation":false,"InspectionDate":"2016-05-12 10:20:00","ProviderID":31039,"AgencyID":0},{"InspectionID":365605,"HasViolation":true,"InspectionDate":"2016-05-09 13:30:00","ProviderID":31039,"AgencyID":0},{"InspectionID":372387,"HasViolation":true,"InspectionDate":"2016-08-18 11:50:00","ProviderID":31039,"AgencyID":0},{"InspectionID":385336,"HasViolation":false,"InspectionDate":"2017-01-04 08:25:00","ProviderID":31039,"AgencyID":0},{"InspectionID":400286,"HasViolation":false,"InspectionDate":"2017-05-10 10:05:00","ProviderID":31039,"AgencyID":0}],"VPKAccreditation":[],"VPKClass":[],"VPKCurriculum":[]},"reportIDs":null,"_displayDistance":true,"Inspections":[{"InspectionID":400286,"HasViolation":false,"InspectionDate":"2017-05-10 10:05:00","ProviderID":31039,"AgencyID":0},{"InspectionID":385336,"HasViolation":false,"InspectionDate":"2017-01-04 08:25:00","ProviderID":31039,"AgencyID":0},{"InspectionID":372387,"HasViolation":true,"InspectionDate":"2016-08-18 11:50:00","ProviderID":31039,"AgencyID":0},{"InspectionID":363278,"HasViolation":false,"InspectionDate":"2016-05-12 10:20:00","ProviderID":31039,"AgencyID":0},{"InspectionID":365605,"HasViolation":true,"InspectionDate":"2016-05-09 13:30:00","ProviderID":31039,"AgencyID":0},{"InspectionID":361547,"HasViolation":true,"InspectionDate":"2016-04-15 10:25:00","ProviderID":31039,"AgencyID":0},{"InspectionID":356663,"HasViolation":true,"InspectionDate":"2016-02-16 13:00:00","ProviderID":31039,"AgencyID":0},{"InspectionID":347040,"HasViolation":true,"InspectionDate":"2015-12-10 13:08:00","ProviderID":31039,"AgencyID":0},{"InspectionID":334990,"HasViolation":true,"InspectionDate":"2015-08-19 08:19:00","ProviderID":31039,"AgencyID":0},{"InspectionID":298791,"HasViolation":false,"InspectionDate":"2015-04-23 11:55:00","ProviderID":31039,"AgencyID":0},{"InspectionID":320123,"HasViolation":true,"InspectionDate":"2015-04-16 13:00:00","ProviderID":31039,"AgencyID":0},{"InspectionID":277010,"HasViolation":false,"InspectionDate":"2015-01-21 15:28:00","ProviderID":31039,"AgencyID":0},{"InspectionID":290707,"HasViolation":true,"InspectionDate":"2015-01-16 10:00:00","ProviderID":31039,"AgencyID":0},{"InspectionID":324931,"HasViolation":false,"InspectionDate":"2014-09-19 14:58:00","ProviderID":31039,"AgencyID":0},{"InspectionID":273684,"HasViolation":true,"InspectionDate":"2014-09-05 10:30:00","ProviderID":31039,"AgencyID":0}],"VPKAccreditation":[],"VPKClass":[],"VPKCurriculum":[],"Distance":"2.91 miles","DisplayServices":{"After School":1,"Drop In":1,"Food Served":1,"Full Day":1,"Half Day":1,"Infant Care":1,"Open Year-Round":1}},{"_distance":6.11437435122334,"Provider":{"ProviderNumber":"C08AL0732 ","Name":"Love-N-Care Preschool","Capacity":43,"LicenseExpirationDate":"03/20/2018","IsReligiousExempt":false,"IsFaithBased":false,"IsHeadStart":false,"IsOfferingSchoolReadiness":true,"IsPublicSchool":false,"OriginationDate":"03/21/2012","ProviderID":33844,"AddressID":5485,"StreetNumber":"12440","StreetPreDirection":"NW","StreetName":"US Highway 441","StreetSuffix":null,"StreetPostDirection":null,"SecondaryDesignatorPrefix":null,"SecondaryDesignatorSuffix":null,"ExtraSecondaryDesignatorPrefix":null,"ExtraSecondaryDesignatorSuffix":null,"City":"Alachua","County":"Alachua","State":"FL","ZipCode":"32615","ZipPlus4":"8508","Latitude":29.768932,"Longitude":-82.423589,"DisplayAddressOnWeb":true,"PhoneNumber":3864180404,"DisplayPhoneOnWeb":true,"ProgramType":"Child Care Facility","Status":"Regular/Annual","Services":"Full Day;Half Day;Infant Care;Open Year-Round","FullAddress":"12440 NW US Highway 441, Alachua FL 32615-8508","GoldSealAccreditingAgency":null,"GoldSealEffectiveDate":null,"GoldSealExpirationDate":null,"GoldSealStatusID":null,"MondayHours":" 6:30AM to 6:00PM","TuesdayHours":" 6:30AM to 6:00PM","WednesdayHours":" 6:30AM to 6:00PM","ThursdayHours":" 6:30AM to 6:00PM","FridayHours":" 6:30AM to 6:00PM","SaturdayHours":null,"SundayHours":null,"LicenseStatus":"Licensed","DBAName":null,"IsVPK":true,"VpkStatusID":2,"AgencyID":2,"AlternateProviderNumber":null,"Inspections":[{"InspectionID":281175,"HasViolation":true,"InspectionDate":"2014-07-01 11:30:00","ProviderID":33844,"AgencyID":0},{"InspectionID":288055,"HasViolation":false,"InspectionDate":"2015-02-26 12:23:00","ProviderID":33844,"AgencyID":0},{"InspectionID":300756,"HasViolation":false,"InspectionDate":"2014-11-06 13:09:00","ProviderID":33844,"AgencyID":0},{"InspectionID":303383,"HasViolation":true,"InspectionDate":"2015-01-08 14:30:00","ProviderID":33844,"AgencyID":0},{"InspectionID":304955,"HasViolation":true,"InspectionDate":"2015-02-20 10:20:00","ProviderID":33844,"AgencyID":0},{"InspectionID":315836,"HasViolation":false,"InspectionDate":"2015-06-12 14:30:00","ProviderID":33844,"AgencyID":0},{"InspectionID":322110,"HasViolation":true,"InspectionDate":"2015-06-05 11:30:00","ProviderID":33844,"AgencyID":0},{"InspectionID":330975,"HasViolation":false,"InspectionDate":"2015-02-17 13:11:00","ProviderID":33844,"AgencyID":0},{"InspectionID":339443,"HasViolation":true,"InspectionDate":"2015-10-06 12:00:00","ProviderID":33844,"AgencyID":0},{"InspectionID":339444,"HasViolation":false,"InspectionDate":"2015-10-07 08:00:00","ProviderID":33844,"AgencyID":0},{"InspectionID":354164,"HasViolation":false,"InspectionDate":"2016-02-08 11:30:00","ProviderID":33844,"AgencyID":0},{"InspectionID":368085,"HasViolation":true,"InspectionDate":"2016-06-30 09:30:00","ProviderID":33844,"AgencyID":0},{"InspectionID":372905,"HasViolation":true,"InspectionDate":"2016-07-12 15:00:00","ProviderID":33844,"AgencyID":0},{"InspectionID":378255,"HasViolation":true,"InspectionDate":"2016-10-11 11:50:00","ProviderID":33844,"AgencyID":0},{"InspectionID":379681,"HasViolation":false,"InspectionDate":"2016-10-18 08:15:00","ProviderID":33844,"AgencyID":0},{"InspectionID":381760,"HasViolation":true,"InspectionDate":"2016-08-11 14:00:00","ProviderID":33844,"AgencyID":0},{"InspectionID":389309,"HasViolation":false,"InspectionDate":"2017-02-09 10:30:00","ProviderID":33844,"AgencyID":0}],"VPKAccreditation":[],"VPKClass":[{"ID":"69eede54-3c96-438a-94d9-9287ae174ab5","ProviderID":33844,"ClassRoomCode":"P1","ClassType":"540","StartDate":"09/01/2016","EndDate":"06/02/2017","Monday":"9:00AM to 12:00PM","Tuesday":"9:00AM to 12:00PM","Wednesday":"9:00AM to 12:00PM","Thursday":"9:00AM to 12:00PM","Friday":"9:00AM to 12:00PM","Saturday":null,"Sunday":null,"ClassRoomCount":1,"Capacity":11,"Enrollments":8,"InstructorCredential":"Florida Equivalent Credential: FCCPC/ECPC/CCAC/CDAE","AgencyID":2}],"VPKCurriculum":[{"ID":"c0d4b645-391f-45a8-a1c7-c035f4e91ac4","ProviderID":33844,"Description":"LEARN EVERY","PublisherName":null},{"ID":"cacd4431-926b-4c49-8e3a-2207d1f258c3","ProviderID":33844,"Description":"Montessori","PublisherName":null}]},"reportIDs":null,"_displayDistance":true,"Inspections":[{"InspectionID":389309,"HasViolation":false,"InspectionDate":"2017-02-09 10:30:00","ProviderID":33844,"AgencyID":0},{"InspectionID":379681,"HasViolation":false,"InspectionDate":"2016-10-18 08:15:00","ProviderID":33844,"AgencyID":0},{"InspectionID":378255,"HasViolation":true,"InspectionDate":"2016-10-11 11:50:00","ProviderID":33844,"AgencyID":0},{"InspectionID":381760,"HasViolation":true,"InspectionDate":"2016-08-11 14:00:00","ProviderID":33844,"AgencyID":0},{"InspectionID":372905,"HasViolation":true,"InspectionDate":"2016-07-12 15:00:00","ProviderID":33844,"AgencyID":0},{"InspectionID":368085,"HasViolation":true,"InspectionDate":"2016-06-30 09:30:00","ProviderID":33844,"AgencyID":0},{"InspectionID":354164,"HasViolation":false,"InspectionDate":"2016-02-08 11:30:00","ProviderID":33844,"AgencyID":0},{"InspectionID":339444,"HasViolation":false,"InspectionDate":"2015-10-07 08:00:00","ProviderID":33844,"AgencyID":0},{"InspectionID":339443,"HasViolation":true,"InspectionDate":"2015-10-06 12:00:00","ProviderID":33844,"AgencyID":0},{"InspectionID":315836,"HasViolation":false,"InspectionDate":"2015-06-12 14:30:00","ProviderID":33844,"AgencyID":0},{"InspectionID":322110,"HasViolation":true,"InspectionDate":"2015-06-05 11:30:00","ProviderID":33844,"AgencyID":0},{"InspectionID":288055,"HasViolation":false,"InspectionDate":"2015-02-26 12:23:00","ProviderID":33844,"AgencyID":0},{"InspectionID":304955,"HasViolation":true,"InspectionDate":"2015-02-20 10:20:00","ProviderID":33844,"AgencyID":0},{"InspectionID":330975,"HasViolation":false,"InspectionDate":"2015-02-17 13:11:00","ProviderID":33844,"AgencyID":0},{"InspectionID":303383,"HasViolation":true,"InspectionDate":"2015-01-08 14:30:00","ProviderID":33844,"AgencyID":0},{"InspectionID":300756,"HasViolation":false,"InspectionDate":"2014-11-06 13:09:00","ProviderID":33844,"AgencyID":0},{"InspectionID":281175,"HasViolation":true,"InspectionDate":"2014-07-01 11:30:00","ProviderID":33844,"AgencyID":0}],"VPKAccreditation":[],"VPKClass":[{"ID":"69eede54-3c96-438a-94d9-9287ae174ab5","ProviderID":33844,"ClassRoomCode":"P1","ClassType":"540","StartDate":"09/01/2016","EndDate":"06/02/2017","Monday":"9:00AM to 12:00PM","Tuesday":"9:00AM to 12:00PM","Wednesday":"9:00AM to 12:00PM","Thursday":"9:00AM to 12:00PM","Friday":"9:00AM to 12:00PM","Saturday":null,"Sunday":null,"ClassRoomCount":1,"Capacity":11,"Enrollments":8,"InstructorCredential":"Florida Equivalent Credential: FCCPC/ECPC/CCAC/CDAE","AgencyID":2}],"VPKCurriculum":[{"ID":"c0d4b645-391f-45a8-a1c7-c035f4e91ac4","ProviderID":33844,"Description":"LEARN EVERY","PublisherName":null},{"ID":"cacd4431-926b-4c49-8e3a-2207d1f258c3","ProviderID":33844,"Description":"Montessori","PublisherName":null}],"Distance":"6.11 miles","DisplayServices":{"Full Day":1,"Half Day":1,"Infant Care":1,"Open Year-Round":1}},{"_distance":6.11437435122334,"Provider":{"ProviderNumber":"E08AL0000 ","Name":"Miss Joni\u0027s Preschool","Capacity":41,"LicenseExpirationDate":null,"IsReligiousExempt":null,"IsFaithBased":null,"IsHeadStart":false,"IsOfferingSchoolReadiness":false,"IsPublicSchool":null,"OriginationDate":null,"ProviderID":16551,"AddressID":5485,"StreetNumber":"12440","StreetPreDirection":"NW","StreetName":"US Highway 441","StreetSuffix":null,"StreetPostDirection":null,"SecondaryDesignatorPrefix":null,"SecondaryDesignatorSuffix":null,"ExtraSecondaryDesignatorPrefix":null,"ExtraSecondaryDesignatorSuffix":null,"City":"Alachua","County":"Alachua","State":"FL","ZipCode":"32615","ZipPlus4":"8508","Latitude":29.768932,"Longitude":-82.423589,"DisplayAddressOnWeb":true,"PhoneNumber":3864180404,"DisplayPhoneOnWeb":true,"ProgramType":"Non-Public School","Status":"Active","Services":"Full Day","FullAddress":"12440 NW US Highway 441, Alachua FL 32615-8508","GoldSealAccreditingAgency":null,"GoldSealEffectiveDate":null,"GoldSealExpirationDate":null,"GoldSealStatusID":null,"MondayHours":" 6:30AM to 6:30PM","TuesdayHours":" 6:30AM to 6:30PM","WednesdayHours":" 6:30AM to 6:30PM","ThursdayHours":" 6:30AM to 6:30PM","FridayHours":" 6:30AM to 6:30PM","SaturdayHours":null,"SundayHours":null,"LicenseStatus":"Exempt","DBAName":null,"IsVPK":false,"VpkStatusID":3,"AgencyID":2,"AlternateProviderNumber":null,"Inspections":[],"VPKAccreditation":[],"VPKClass":[],"VPKCurriculum":[]},"reportIDs":null,"_displayDistance":true,"Inspections":[],"VPKAccreditation":[],"VPKClass":[],"VPKCurriculum":[],"Distance":"6.11 miles","DisplayServices":{"Full Day":1}},{"_distance":7.96516992984861,"Provider":{"ProviderNumber":"C08AL0757 ","Name":"Forest Grove Christian Academy","Capacity":54,"LicenseExpirationDate":"07/28/2017","IsReligiousExempt":false,"IsFaithBased":false,"IsHeadStart":false,"IsOfferingSchoolReadiness":false,"IsPublicSchool":false,"OriginationDate":"07/29/2015","ProviderID":38395,"AddressID":3401,"StreetNumber":"22575","StreetPreDirection":"NW","StreetName":"94th","StreetSuffix":"Ave","StreetPostDirection":null,"SecondaryDesignatorPrefix":null,"SecondaryDesignatorSuffix":null,"ExtraSecondaryDesignatorPrefix":null,"ExtraSecondaryDesignatorSuffix":null,"City":"Alachua","County":"Alachua","State":"FL","ZipCode":"32615","ZipPlus4":"5915","Latitude":29.741426,"Longitude":-82.581353,"DisplayAddressOnWeb":true,"PhoneNumber":3864623921,"DisplayPhoneOnWeb":true,"ProgramType":"Child Care Facility","Status":"Regular/Annual","Services":"After School;Full Day;Open Year-Round","FullAddress":"22575 NW 94th Ave, Alachua FL 32615-5915","GoldSealAccreditingAgency":null,"GoldSealEffectiveDate":null,"GoldSealExpirationDate":null,"GoldSealStatusID":null,"MondayHours":" 7:30AM to 5:30PM","TuesdayHours":" 7:30AM to 5:30PM","WednesdayHours":" 7:30AM to 5:30PM","ThursdayHours":" 7:30AM to 5:30PM","FridayHours":" 7:30AM to 5:30PM","SaturdayHours":null,"SundayHours":null,"LicenseStatus":"Licensed","DBAName":null,"IsVPK":true,"VpkStatusID":2,"AgencyID":2,"AlternateProviderNumber":null,"Inspections":[{"InspectionID":279751,"HasViolation":false,"InspectionDate":"2015-07-22 15:00:00","ProviderID":38395,"AgencyID":0},{"InspectionID":339910,"HasViolation":true,"InspectionDate":"2015-10-14 08:30:00","ProviderID":38395,"AgencyID":0},{"InspectionID":342872,"HasViolation":false,"InspectionDate":"2015-10-28 13:06:00","ProviderID":38395,"AgencyID":0},{"InspectionID":357008,"HasViolation":true,"InspectionDate":"2016-03-04 10:20:00","ProviderID":38395,"AgencyID":0},{"InspectionID":359011,"HasViolation":false,"InspectionDate":"2016-03-18 08:48:00","ProviderID":38395,"AgencyID":0},{"InspectionID":367623,"HasViolation":true,"InspectionDate":"2016-06-22 13:20:00","ProviderID":38395,"AgencyID":0},{"InspectionID":368827,"HasViolation":false,"InspectionDate":"2016-07-13 13:15:00","ProviderID":38395,"AgencyID":0},{"InspectionID":378448,"HasViolation":true,"InspectionDate":"2016-10-13 12:50:00","ProviderID":38395,"AgencyID":0},{"InspectionID":389969,"HasViolation":true,"InspectionDate":"2017-02-15 11:15:00","ProviderID":38395,"AgencyID":0},{"InspectionID":392102,"HasViolation":false,"InspectionDate":"2017-03-06 07:21:00","ProviderID":38395,"AgencyID":0}],"VPKAccreditation":[],"VPKClass":[{"ID":"be6f7283-ce56-4abc-89ff-ff2e4cab73a4","ProviderID":38395,"ClassRoomCode":"P1","ClassType":"540","StartDate":"08/15/2016","EndDate":"06/03/2017","Monday":"8:00AM to 11:00AM","Tuesday":"8:00AM to 11:00AM","Wednesday":"8:00AM to 11:00AM","Thursday":"8:00AM to 11:00AM","Friday":"8:00AM to 11:00AM","Saturday":null,"Sunday":null,"ClassRoomCount":1,"Capacity":20,"Enrollments":11,"InstructorCredential":"Master\u0027s Degree","AgencyID":2}],"VPKCurriculum":[]},"reportIDs":null,"_displayDistance":true,"Inspections":[{"InspectionID":392102,"HasViolation":false,"InspectionDate":"2017-03-06 07:21:00","ProviderID":38395,"AgencyID":0},{"InspectionID":389969,"HasViolation":true,"InspectionDate":"2017-02-15 11:15:00","ProviderID":38395,"AgencyID":0},{"InspectionID":378448,"HasViolation":true,"InspectionDate":"2016-10-13 12:50:00","ProviderID":38395,"AgencyID":0},{"InspectionID":368827,"HasViolation":false,"InspectionDate":"2016-07-13 13:15:00","ProviderID":38395,"AgencyID":0},{"InspectionID":367623,"HasViolation":true,"InspectionDate":"2016-06-22 13:20:00","ProviderID":38395,"AgencyID":0},{"InspectionID":359011,"HasViolation":false,"InspectionDate":"2016-03-18 08:48:00","ProviderID":38395,"AgencyID":0},{"InspectionID":357008,"HasViolation":true,"InspectionDate":"2016-03-04 10:20:00","ProviderID":38395,"AgencyID":0},{"InspectionID":342872,"HasViolation":false,"InspectionDate":"2015-10-28 13:06:00","ProviderID":38395,"AgencyID":0},{"InspectionID":339910,"HasViolation":true,"InspectionDate":"2015-10-14 08:30:00","ProviderID":38395,"AgencyID":0},{"InspectionID":279751,"HasViolation":false,"InspectionDate":"2015-07-22 15:00:00","ProviderID":38395,"AgencyID":0}],"VPKAccreditation":[],"VPKClass":[{"ID":"be6f7283-ce56-4abc-89ff-ff2e4cab73a4","ProviderID":38395,"ClassRoomCode":"P1","ClassType":"540","StartDate":"08/15/2016","EndDate":"06/03/2017","Monday":"8:00AM to 11:00AM","Tuesday":"8:00AM to 11:00AM","Wednesday":"8:00AM to 11:00AM","Thursday":"8:00AM to 11:00AM","Friday":"8:00AM to 11:00AM","Saturday":null,"Sunday":null,"ClassRoomCount":1,"Capacity":20,"Enrollments":11,"InstructorCredential":"Master\u0027s Degree","AgencyID":2}],"VPKCurriculum":[],"Distance":"7.97 miles","DisplayServices":{"After School":1,"Full Day":1,"Open Year-Round":1}},{"_distance":9999,"Provider":{"ProviderNumber":"L08AL0016 ","Name":"Attentive Childcare \u0026 Pre-k","Capacity":12,"LicenseExpirationDate":"02/03/2018","IsReligiousExempt":false,"IsFaithBased":false,"IsHeadStart":false,"IsOfferingSchoolReadiness":false,"IsPublicSchool":false,"OriginationDate":"02/04/2016","ProviderID":263760,"AddressID":31827,"StreetNumber":"NA","StreetPreDirection":null,"StreetName":"NA","StreetSuffix":null,"StreetPostDirection":null,"SecondaryDesignatorPrefix":null,"SecondaryDesignatorSuffix":null,"ExtraSecondaryDesignatorPrefix":null,"ExtraSecondaryDesignatorSuffix":null,"City":"Alachua","County":"Alachua","State":"FL","ZipCode":"32615","ZipPlus4":null,"Latitude":null,"Longitude":null,"DisplayAddressOnWeb":true,"PhoneNumber":3864180682,"DisplayPhoneOnWeb":true,"ProgramType":"Large Family Child Care Home","Status":"Regular/Annual","Services":"After School;Food Served;Full Day;Half Day;Infant Care;Open Year-Round","FullAddress":"16717 NW 173rd Ter, Alachua FL, 32615 #1, Alachua FL, 32615","GoldSealAccreditingAgency":null,"GoldSealEffectiveDate":null,"GoldSealExpirationDate":null,"GoldSealStatusID":null,"MondayHours":" 7:00AM to 7:00PM","TuesdayHours":" 7:00AM to 7:00PM","WednesdayHours":" 7:00AM to 7:00PM","ThursdayHours":" 7:00AM to 7:00PM","FridayHours":" 7:00AM to 7:00PM","SaturdayHours":null,"SundayHours":null,"LicenseStatus":"Licensed","DBAName":"Attentive Childcare \u0026 Pre-k","IsVPK":false,"VpkStatusID":1,"AgencyID":2,"AlternateProviderNumber":null,"Inspections":[{"InspectionID":353950,"HasViolation":false,"InspectionDate":"2016-02-03 12:22:00","ProviderID":263760,"AgencyID":0},{"InspectionID":370327,"HasViolation":true,"InspectionDate":"2016-07-19 09:55:00","ProviderID":263760,"AgencyID":0},{"InspectionID":385339,"HasViolation":false,"InspectionDate":"2017-01-04 11:45:00","ProviderID":263760,"AgencyID":0}],"VPKAccreditation":[],"VPKClass":[],"VPKCurriculum":[]},"reportIDs":null,"_displayDistance":false,"Inspections":[{"InspectionID":385339,"HasViolation":false,"InspectionDate":"2017-01-04 11:45:00","ProviderID":263760,"AgencyID":0},{"InspectionID":370327,"HasViolation":true,"InspectionDate":"2016-07-19 09:55:00","ProviderID":263760,"AgencyID":0},{"InspectionID":353950,"HasViolation":false,"InspectionDate":"2016-02-03 12:22:00","ProviderID":263760,"AgencyID":0}],"VPKAccreditation":[],"VPKClass":[],"VPKCurriculum":[],"Distance":"N/A","DisplayServices":{"After School":1,"Food Served":1,"Full Day":1,"Half Day":1,"Infant Care":1,"Open Year-Round":1}},{"_distance":9999,"Provider":{"ProviderNumber":"L08AL0464 ","Name":"Pattie-Cake Christian Academy","Capacity":12,"LicenseExpirationDate":"11/20/2017","IsReligiousExempt":false,"IsFaithBased":false,"IsHeadStart":false,"IsOfferingSchoolReadiness":true,"IsPublicSchool":false,"OriginationDate":"11/21/2011","ProviderID":31988,"AddressID":9078,"StreetNumber":"13805","StreetPreDirection":"NW","StreetName":"155th","StreetSuffix":"Ave","StreetPostDirection":null,"SecondaryDesignatorPrefix":null,"SecondaryDesignatorSuffix":null,"ExtraSecondaryDesignatorPrefix":null,"ExtraSecondaryDesignatorSuffix":null,"City":"Alachua","County":"Alachua","State":"FL","ZipCode":"32615","ZipPlus4":"5870","Latitude":29.796785,"Longitude":-82.492449,"DisplayAddressOnWeb":false,"PhoneNumber":3864627194,"DisplayPhoneOnWeb":true,"ProgramType":"Large Family Child Care Home","Status":"Regular/Annual","Services":"After School;Before School;Drop In;Food Served;Full Day;Half Day;Infant Care;Night Care;School Year Only;Weekend Care","FullAddress":"13805 NW 155th Ave, Alachua FL 32615-5870","GoldSealAccreditingAgency":null,"GoldSealEffectiveDate":null,"GoldSealExpirationDate":null,"GoldSealStatusID":null,"MondayHours":" 12:00AM to 11:59PM","TuesdayHours":" 12:00AM to 11:59PM","WednesdayHours":" 12:00AM to 11:59PM","ThursdayHours":" 12:00AM to 11:59PM","FridayHours":" 12:00AM to 11:59PM","SaturdayHours":" 12:00AM to 11:59PM","SundayHours":" 12:00AM to 11:59PM","LicenseStatus":"Licensed","DBAName":"Pattie-Cake Christian Academy","IsVPK":false,"VpkStatusID":1,"AgencyID":2,"AlternateProviderNumber":null,"Inspections":[{"InspectionID":258943,"HasViolation":false,"InspectionDate":"2014-11-12 08:15:00","ProviderID":31988,"AgencyID":0},{"InspectionID":261233,"HasViolation":true,"InspectionDate":"2014-11-07 11:04:00","ProviderID":31988,"AgencyID":0},{"InspectionID":280425,"HasViolation":true,"InspectionDate":"2015-04-16 12:00:00","ProviderID":31988,"AgencyID":0},{"InspectionID":293780,"HasViolation":false,"InspectionDate":"2015-04-27 11:03:00","ProviderID":31988,"AgencyID":0},{"InspectionID":339958,"HasViolation":true,"InspectionDate":"2015-10-09 08:40:00","ProviderID":31988,"AgencyID":0},{"InspectionID":339985,"HasViolation":false,"InspectionDate":"2015-10-15 09:02:00","ProviderID":31988,"AgencyID":0},{"InspectionID":362053,"HasViolation":false,"InspectionDate":"2016-04-26 14:10:00","ProviderID":31988,"AgencyID":0},{"InspectionID":379921,"HasViolation":true,"InspectionDate":"2016-10-19 09:47:00","ProviderID":31988,"AgencyID":0},{"InspectionID":380339,"HasViolation":false,"InspectionDate":"2016-10-25 08:34:00","ProviderID":31988,"AgencyID":0},{"InspectionID":400297,"HasViolation":false,"InspectionDate":"2017-05-10 11:30:00","ProviderID":31988,"AgencyID":0}],"VPKAccreditation":[],"VPKClass":[],"VPKCurriculum":[]},"reportIDs":null,"_displayDistance":false,"Inspections":[{"InspectionID":400297,"HasViolation":false,"InspectionDate":"2017-05-10 11:30:00","ProviderID":31988,"AgencyID":0},{"InspectionID":380339,"HasViolation":false,"InspectionDate":"2016-10-25 08:34:00","ProviderID":31988,"AgencyID":0},{"InspectionID":379921,"HasViolation":true,"InspectionDate":"2016-10-19 09:47:00","ProviderID":31988,"AgencyID":0},{"InspectionID":362053,"HasViolation":false,"InspectionDate":"2016-04-26 14:10:00","ProviderID":31988,"AgencyID":0},{"InspectionID":339985,"HasViolation":false,"InspectionDate":"2015-10-15 09:02:00","ProviderID":31988,"AgencyID":0},{"InspectionID":339958,"HasViolation":true,"InspectionDate":"2015-10-09 08:40:00","ProviderID":31988,"AgencyID":0},{"InspectionID":293780,"HasViolation":false,"InspectionDate":"2015-04-27 11:03:00","ProviderID":31988,"AgencyID":0},{"InspectionID":280425,"HasViolation":true,"InspectionDate":"2015-04-16 12:00:00","ProviderID":31988,"AgencyID":0},{"InspectionID":258943,"HasViolation":false,"InspectionDate":"2014-11-12 08:15:00","ProviderID":31988,"AgencyID":0},{"InspectionID":261233,"HasViolation":true,"InspectionDate":"2014-11-07 11:04:00","ProviderID":31988,"AgencyID":0}],"VPKAccreditation":[],"VPKClass":[],"VPKCurriculum":[],"Distance":"N/A","DisplayServices":{"After School":1,"Before School":1,"Drop In":1,"Food Served":1,"Full Day":1,"Half Day":1,"Infant Care":1,"Night Care":1,"School Year Only":1,"Weekend Care":1}}]